sarkit_convert-0.2.0.dist-info/METADATA
sarkit_convert-0.2.0.dist-info/WHEEL
sarkit_convert-0.2.0.dist-info/entry_points.txt
sarkit_convert-0.2.0.dist-info/licenses/LICENSE
sarkit_convert/__init__.py
sarkit_convert/_utils.py
sarkit_convert/_version.py
sarkit_convert/cosmo.py
sarkit_convert/create_arp_poly.py
sarkit_convert/iceye.py
sarkit_convert/sentinel.py
sarkit_convert/sidd_metadata.py
sarkit_convert/terrasar.py
sarkit_convert-0.2.0.dist-info/RECORD
